{
  "continents": [
    {
      "id": "afrique",
      "name_en": "Africa",
      "name_fr": "Afrique",
      "countries": []
    },
    {
      "id": "amerique_du_nord",
      "name_en": "North America",
      "name_fr": "Amérique du Nord",
      "countries": [
        {
          "id": "canada",
          "name_en": "Canada",
          "name_fr": "Canada",
          "dioceses": []
        }
      ]
    },
    {
      "id": "europe",
      "name_en": "Europe",
      "name_fr": "Europe",
      "countries": [
        {
          "id": "france",
          "name_en": "France",
          "name_fr": "France",
          "dioceses": [
            {
              "id": "bordeaux",
              "name_en": "Bordeaux",
              "name_fr": "Bordeaux",
              "churches": [
                {
                  "id": "bordeaux_cathedrale",
                  "name_en": "Cathedral of Saint Andrew",
                  "name_fr": "Cathédrale Saint-André"
                }
              ]
            },
            {
              "id": "lille",
              "name_en": "Lille",
              "name_fr": "Lille"
            },
            {
              "id": "lyon",
              "name_en": "Lyon",
              "name_fr": "Lyon",
              "churches": [
                {
                  "id": "lyon_primatiale",
                  "name_en": "Primatiale Saint-Jean",
                  "name_fr": "Primatiale Saint-Jean"
                }
              ]
            },
            {
              "id": "paris",
              "name_en": "Paris",
              "name_fr": "Paris"
            }
          ]
        },
        {
          "id": "belgique",
          "name_en": "Belgium",
          "name_fr": "Belgique",
          "dioceses": []
        },
        {
          "id": "luxembourg",
          "name_en": "Luxembourg",
          "name_fr": "Luxembourg",
          "dioceses": []
        },
        {
          "id": "suisse",
          "name_en": "Switzerland",
          "name_fr": "Suisse",
          "dioceses": []
        },
        {
          "id": "monaco",
          "name_en": "Monaco",
          "name_fr": "Monaco",
          "dioceses": []
        }
      ]
    },
    {
      "id": "romain",
      "name_en": "Other (Roman Calendar)",
      "name_fr": "Autre (Calendrier romain)",
      "countries": []
    }
  ]
}