{
  "invitatoryAntiphon1": "Aujourd’hui, ne fermons pas notre cœur, mais écoutons la voix du Seigneur.",
  "invitatoryAntiphon2": "Les yeux fixés sur Jésus Christ, entrons dans le combat de Dieu.",
  "morningPsalm3Antiphon1": "Tous rassemblés, nous bénirons le Seigneur éternel.",
  "morningPsalm2Antiphon1": "Glorifie le Seigneur, Jérusalem ! Célèbre ton Dieu, ô Sion !",
  "morningPsalm1Antiphon1": "Tu ne repousses pas, mon Dieu, un cœur brisé.",
  "morningEvangelicAntiphon": "Je ne suis pas venu de moi-même, c’est mon Père qui m’a envoyé."
}