{
  "celebrationTitle": "Saint Pierre Damien",
  "celebrationSubtitle": "évêque et docteur de l'Église",
  "celebrationDescription": "Pierre Damien, né à Ravenne (1007), mena la vie érémitique à Font Avellane avant de devenir le collaborateur des papes pour la réforme de l’Église. Fait cardinal évêque d’Ostie (1057), chargé de multiples légations en Italie, en France et en Allemagne, il mena une lutte énergique pour rendre au clergé sa dignité et à l’Église la liberté († 1072).",
  "liturgicalGrade": 12,
  "liturgicalColor": "white",
  "commons": ["pastors_bishop", "doctors"],
  "readingsPatristicReadingTitle": "",
  "readingsPatristicReadingSubtitle": "",
  "readingsPatristicReadingContent": "(texte à trouver)",
  "readingsPatristicReadingResponsory": "(texte à trouver)",
  "oration": "Accorde-nous, Dieu tout-puissant, de suivre les exemples et les exhortations du saint évêque Pierre Damien, afin que, sans rien préférer au Christ, et toujours "
}
